mcp_linear/__init__.py
mcp_linear/linear_client.py
mcp_linear/main.py
mcp_linear-0.1.1.dist-info/licenses/LICENSE
mcp_linear-0.1.1.dist-info/METADATA
mcp_linear-0.1.1.dist-info/WHEEL
mcp_linear-0.1.1.dist-info/entry_points.txt
mcp_linear-0.1.1.dist-info/top_level.txt
mcp_linear-0.1.1.dist-info/RECORD
