Metadata-Version: 2.4
Name: mcp-linear
Version: 0.1.1
Summary: Linear MCP Server
Author-email: Vinayak Mehta <vmehta94@gmail.com>
License: MIT
Project-URL: Homepage, https://github.com/vinayak-mehta/linear-mcp
Project-URL: Bug Tracker, https://github.com/vinayak-mehta/linear-mcp/issues
Classifier: License :: OSI Approved :: Apache Software License
Requires-Python: >=3.10
License-File: LICENSE
Requires-Dist: httpx>=0.24.0
Requires-Dist: mcp>=0.1.0
Requires-Dist: python-dotenv>=1.0.0
Dynamic: license-file
